datamigrato/__init__.py
datamigrato/adapters/__init__.py
datamigrato/adapters/cassandra_adapter.py
datamigrato/adapters/firebase_realtime_adapter.py
datamigrato/adapters/firestore_adapter.py
datamigrato/adapters/mongodb_adapter.py
datamigrato/handler/__init__.py
datamigrato/handler/datamigrato_handler.py
datamigrato/migration/__init__.py
datamigrato/migration/base_migrator.py
datamigrato/migration/cassandra_migrator.py
datamigrato/migration/firebase_realtime_migrator.py
datamigrato/migration/firestore_migrator.py
datamigrato/migration/mongodb_migrator.py
datamigrato/utils/__init__.py
datamigrato/utils/common_utils.py
datamigrato/utils/custom_exception.py
datamigrato-0.4.1.dist-info/METADATA
datamigrato-0.4.1.dist-info/WHEEL
datamigrato-0.4.1.dist-info/top_level.txt
datamigrato-0.4.1.dist-info/RECORD
