Metadata-Version: 2.1
Name: datamigrato
Version: 0.4.1
Summary: A Python package for migrating data between various databases.
Home-page: https://github.com/ritikdutta/datamigrato
Author: ritikdutta
Author-email: ritikduttagd@gmail.com
License: MIT
Project-URL: Bug Tracker, https://github.com/ritikdutta/datamigrato/issues
Classifier: Programming Language :: Python :: 3.7
Classifier: Programming Language :: Python :: 3.8
Classifier: Programming Language :: Python :: 3.9
Classifier: Operating System :: OS Independent
Requires-Python: >=3.7
Requires-Dist: ensure ==1.0.2
Requires-Dist: pymongo ==4.6.1
Requires-Dist: cassandra-driver ==3.29.0
Requires-Dist: tabulate ==0.9.0
Requires-Dist: pytz ==2023.3.post1
Requires-Dist: pyyaml ==6.0.1
Requires-Dist: pandas
Requires-Dist: astrapy
Requires-Dist: firebase-admin ==6.4.0
Provides-Extra: testing
Requires-Dist: pytest >=7.1.3 ; extra == 'testing'
Requires-Dist: mypy >=0.971 ; extra == 'testing'
Requires-Dist: flake8 >=5.0.4 ; extra == 'testing'
Requires-Dist: tox >=3.25.1 ; extra == 'testing'
Requires-Dist: black >=22.8.0 ; extra == 'testing'
